attrdictx/__init__.py
attrdictx/attrdictx.py
attrdictx-0.1.0.dist-info/LICENSE
attrdictx-0.1.0.dist-info/METADATA
attrdictx-0.1.0.dist-info/WHEEL
attrdictx-0.1.0.dist-info/top_level.txt
attrdictx-0.1.0.dist-info/RECORD
