Metadata-Version: 2.1
Name: attrdictx
Version: 0.1.0
Summary: An extended AttrDict class
Home-page: https://github.com/kyo-takano/attrdictx
Author: Kyo Takano
Author-email: kyo.takano@mentalese.co
License: UNKNOWN
Platform: UNKNOWN
Classifier: License :: OSI Approved :: MIT License
Classifier: Programming Language :: Python :: 3
Requires-Python: >=3.6
